AUTHORS.rst
CONTRIBUTING.rst
HISTORY.rst
LICENSE.txt
MANIFEST.in
README.rst
setup.cfg
setup.py
versioneer.py
docs/Makefile
docs/api.rst
docs/authors.rst
docs/conf.py
docs/contributing.rst
docs/history.rst
docs/index.rst
docs/installation.rst
docs/make.bat
docs/readme.rst
docs/usage.rst
mplview/__init__.py
mplview/_version.py
mplview/core.py
mplview.egg-info/PKG-INFO
mplview.egg-info/SOURCES.txt
mplview.egg-info/dependency_links.txt
mplview.egg-info/not-zip-safe
mplview.egg-info/requires.txt
mplview.egg-info/top_level.txt
tests/__init__.py
tests/test_core.py